pyramid_sendgrid_webhooks/__init__.py
pyramid_sendgrid_webhooks/errors.py
pyramid_sendgrid_webhooks/parser.py
pyramid_sendgrid_webhooks/pyramid_sendgrid_webhooks.py
pyramid_sendgrid_webhooks/events/__init__.py
pyramid_sendgrid_webhooks/events/base.py
pyramid_sendgrid_webhooks/events/delivery.py
pyramid_sendgrid_webhooks/events/engagement.py
pyramid_sendgrid_webhooks-1.2.3.dist-info/DESCRIPTION.rst
pyramid_sendgrid_webhooks-1.2.3.dist-info/METADATA
pyramid_sendgrid_webhooks-1.2.3.dist-info/metadata.json
pyramid_sendgrid_webhooks-1.2.3.dist-info/RECORD
pyramid_sendgrid_webhooks-1.2.3.dist-info/top_level.txt
pyramid_sendgrid_webhooks-1.2.3.dist-info/WHEEL
