Metadata-Version: 2.0
Name: pyramid-sendgrid-webhooks
Version: 1.2.3
Summary: Parses incoming Sendgrid Webhooks in Pyramid apps
Home-page: https://github.com/GoodRx/pyramid-sendgrid-webhooks
Author: Kyle Stark
Author-email: kyle@goodrx.com
License: MIT
Keywords: pyramid_sendgrid_webhooks
Platform: UNKNOWN
Classifier: Development Status :: 4 - Beta
Classifier: Intended Audience :: Developers
Classifier: License :: OSI Approved :: MIT License
Classifier: Natural Language :: English
Classifier: Programming Language :: Python :: 2
Classifier: Programming Language :: Python :: 2.7
Classifier: Programming Language :: Python :: 3
Classifier: Programming Language :: Python :: 3.3
Classifier: Programming Language :: Python :: 3.4
Classifier: Programming Language :: Python :: 3.5
Classifier: Framework :: Pyramid
Requires-Dist: pyramid (>=1.4.0)
